forte.health-0.1.0-py3.7-nspkg.pth
fortex/health/__init__.py
ftx/medical/__init__.py
ftx/medical/clinical_ontology.py
forte.health-0.1.0.dist-info/LICENSE
forte.health-0.1.0.dist-info/METADATA
forte.health-0.1.0.dist-info/WHEEL
forte.health-0.1.0.dist-info/entry_points.txt
forte.health-0.1.0.dist-info/namespace_packages.txt
forte.health-0.1.0.dist-info/top_level.txt
forte.health-0.1.0.dist-info/RECORD
