Metadata-Version: 2.1
Name: forte.health
Version: 0.1.0
Summary: NLP pipeline framework for biomedical and clinical domains
Home-page: https://github.com/asyml/ForteHealth
License: Apache License Version 2.0
Requires-Python: >=3.6
License-File: LICENSE
Requires-Dist: forte (~=0.2.0)
Requires-Dist: sortedcontainers (==2.1.0)
Requires-Dist: numpy (>=1.16.6)
Requires-Dist: jsonpickle (==1.4)
Requires-Dist: pyyaml (==5.4)
Requires-Dist: smart-open (>=1.8.4)
Requires-Dist: typed-astunparse (==2.1.4)
Requires-Dist: funcsigs (==1.0.2)
Requires-Dist: mypy-extensions (==0.4.3)
Requires-Dist: typed-ast (>=1.4.3)
Requires-Dist: jsonschema (==3.0.2)
Requires-Dist: texar-pytorch
Requires-Dist: typing-inspect (>=0.6.0)
Requires-Dist: fastapi (==0.65.2)
Requires-Dist: uvicorn (==0.14.0)
Requires-Dist: typing (>=3.7.4) ; python_version < "3.5"
Requires-Dist: dataclasses (~=0.7) ; python_version < "3.7"
Requires-Dist: importlib-resources (==5.1.4) ; python_version < "3.7"
Provides-Extra: test
Requires-Dist: ddt ; extra == 'test'
Requires-Dist: testfixtures ; extra == 'test'
Requires-Dist: transformers (==4.2.2) ; extra == 'test'
Requires-Dist: protobuf (==3.19.4) ; extra == 'test'
